chibi_site/__init__.py
chibi_site/chibi_file.py
chibi_site/chibi_site.py
chibi_site/path.py
chibi_site/soup.py
chibi_site-0.1.1.dist-info/licenses/AUTHORS.rst
chibi_site-0.1.1.dist-info/licenses/LICENSE
chibi_site-0.1.1.dist-info/METADATA
chibi_site-0.1.1.dist-info/WHEEL
chibi_site-0.1.1.dist-info/top_level.txt
chibi_site-0.1.1.dist-info/RECORD
