Metadata-Version: 2.4
Name: chibi_site
Version: 0.1.1
Summary: libreria para hacer scrappers de sitios web
Home-page: https://github.com/dem4ply/chibi_site
Author: dem4ply
Author-email: dem4ply@gmail.com
License: WTFPL
Keywords: chibi_site
Classifier: Development Status :: 2 - Pre-Alpha
Classifier: Intended Audience :: Developers
Classifier: License :: Public Domain
Classifier: Natural Language :: English
Classifier: Programming Language :: Python :: 3.7
Classifier: Programming Language :: Python :: 3.8
License-File: LICENSE
License-File: AUTHORS.rst
Requires-Dist: chibi>=0.16.0
Requires-Dist: chibi_requests>=1.3.1
Requires-Dist: selenium>=4.29.0
Dynamic: author
Dynamic: author-email
Dynamic: classifier
Dynamic: description
Dynamic: home-page
Dynamic: keywords
Dynamic: license
Dynamic: license-file
Dynamic: requires-dist
Dynamic: summary
